model_revisioning/__init__.py
model_revisioning/admin.py
model_revisioning/base.py
model_revisioning/fields.py
model_revisioning/management/__init__.py
model_revisioning/management/commands/__init__.py
model_revisioning/management/commands/graph_revision.py
model_revisioning/managers.py
model_revisioning/models.py
model_revisioning/options.py
model_revisioning/signals.py
model_revisioning/templates/model_revisioning/change_form.html
model_revisioning/templates/model_revisioning/revisions.html
model_revisioning/templatetags/__init__.py
model_revisioning/templatetags/model_revisioning_tags.py
django_model_revisioning-0.0.1a3.dist-info/LICENSE
django_model_revisioning-0.0.1a3.dist-info/WHEEL
django_model_revisioning-0.0.1a3.dist-info/METADATA
django_model_revisioning-0.0.1a3.dist-info/RECORD
