Metadata-Version: 2.1
Name: django-model-revisioning
Version: 0.0.1a3
Summary: Version control for django models.
Home-page: https://github.com/valberg/django-model-revisioning
License: GPL-3.0+
Author: Vidir Valberg Gudmundsson
Author-email: valberg@orn.li
Requires-Python: >=3.6,<4.0
Classifier: Development Status :: 3 - Alpha
Classifier: Framework :: Django
Classifier: Framework :: Django :: 2.2
Classifier: License :: OSI Approved :: GNU General Public License v3 or later (GPLv3+)
Classifier: Programming Language :: Python :: 3
Classifier: Programming Language :: Python :: 3.6
Classifier: Programming Language :: Python :: 3.7
Classifier: Topic :: Software Development :: Libraries :: Python Modules
Requires-Dist: django (>=2.2,<3.0)
Project-URL: Documentation, https://django-model-revisioning.readthedocs.io
Project-URL: Repository, https://github.com/valberg/django-model-revisioning
